dag_cbor/__init__.py
dag_cbor/ipld.py
dag_cbor/py.typed
dag_cbor/random.py
dag_cbor/decoding/__init__.py
dag_cbor/decoding/_err.py
dag_cbor/decoding/_err_utils.py
dag_cbor/decoding/_stream.py
dag_cbor/decoding/err.py
dag_cbor/encoding/__init__.py
dag_cbor/encoding/err.py
dag_cbor-0.3.3.dist-info/LICENSE
dag_cbor-0.3.3.dist-info/METADATA
dag_cbor-0.3.3.dist-info/WHEEL
dag_cbor-0.3.3.dist-info/top_level.txt
dag_cbor-0.3.3.dist-info/RECORD
