Metadata-Version: 2.1
Name: dag-cbor
Version: 0.3.3
Summary: Python implementation of the DAG-CBOR codec.
Home-page: https://github.com/hashberg-io/dag-cbor
Author: hashberg
Author-email: sg495@users.noreply.github.com
Project-URL: Bug Tracker, https://github.com/hashberg-io/dag-cbor/issues
Classifier: Development Status :: 4 - Beta
Classifier: Programming Language :: Python :: 3.10
Classifier: Programming Language :: Python :: 3.9
Classifier: Programming Language :: Python :: 3.8
Classifier: Programming Language :: Python :: 3.7
Classifier: Operating System :: OS Independent
Classifier: Natural Language :: English
Classifier: Typing :: Typed
Requires-Python: >=3.7
License-File: LICENSE
Requires-Dist: typing-extensions >=4.6.0
Requires-Dist: typing-validation >=1.1.0
Requires-Dist: multiformats >=0.3.1
